tuberiassantiago/__init__.py
tuberiassantiago/matematicas.py
tuberiassantiago-0.1.0.dist-info/METADATA
tuberiassantiago-0.1.0.dist-info/WHEEL
tuberiassantiago-0.1.0.dist-info/RECORD
