Metadata-Version: 2.1
Name: tuberiassantiago
Version: 0.1.0
Summary: Descripción del paquete
Home-page: https://github.com/….
Author: Santiago
Author-email: lsquinones@gmail.com
Requires-Python: >=3.10.0,<3.12
Classifier: Programming Language :: Python :: 3
Classifier: Programming Language :: Python :: 3.10
Classifier: Programming Language :: Python :: 3.11
Project-URL: Repository, https://github.com/….
Project-URL: repository, https://github.com/…
